geek_cafe_services/__init__.py
geek_cafe_services/core/__init__.py
geek_cafe_services/core/audit_mixin.py
geek_cafe_services/core/service_errors.py
geek_cafe_services/core/service_result.py
geek_cafe_services/lambda_handlers/__init__.py
geek_cafe_services/lambda_handlers/_base/__init__.py
geek_cafe_services/lambda_handlers/_base/api_key_handler.py
geek_cafe_services/lambda_handlers/_base/base_handler.py
geek_cafe_services/lambda_handlers/_base/handler_factory.py
geek_cafe_services/lambda_handlers/_base/public_handler.py
geek_cafe_services/lambda_handlers/_base/secure_handler.py
geek_cafe_services/lambda_handlers/_base/service_pool.py
geek_cafe_services/lambda_handlers/events/create/app.py
geek_cafe_services/lambda_handlers/events/delete/app.py
geek_cafe_services/lambda_handlers/events/get/app.py
geek_cafe_services/lambda_handlers/events/list/app.py
geek_cafe_services/lambda_handlers/events/update/app.py
geek_cafe_services/lambda_handlers/groups/create/app.py
geek_cafe_services/lambda_handlers/groups/delete/app.py
geek_cafe_services/lambda_handlers/groups/get/app.py
geek_cafe_services/lambda_handlers/groups/list/app.py
geek_cafe_services/lambda_handlers/groups/update/app.py
geek_cafe_services/lambda_handlers/messages/create/app.py
geek_cafe_services/lambda_handlers/messages/delete/app.py
geek_cafe_services/lambda_handlers/messages/get/app.py
geek_cafe_services/lambda_handlers/messages/list/app.py
geek_cafe_services/lambda_handlers/messages/update/app.py
geek_cafe_services/lambda_handlers/users/create/app.py
geek_cafe_services/lambda_handlers/users/delete/app.py
geek_cafe_services/lambda_handlers/users/get/app.py
geek_cafe_services/lambda_handlers/users/list/app.py
geek_cafe_services/lambda_handlers/users/update/app.py
geek_cafe_services/lambda_handlers/votes/create/app.py
geek_cafe_services/lambda_handlers/votes/delete/app.py
geek_cafe_services/lambda_handlers/votes/get/app.py
geek_cafe_services/lambda_handlers/votes/list/app.py
geek_cafe_services-0.4.5.dist-info/METADATA
geek_cafe_services-0.4.5.dist-info/WHEEL
geek_cafe_services-0.4.5.dist-info/licenses/LICENSE
geek_cafe_services-0.4.5.dist-info/RECORD
