Metadata-Version: 2.4
Name: geek_cafe_services
Version: 0.4.5
Summary: Base Reusable Services for SaaS
Project-URL: Homepage, https://github.com/geekcafe/geek-cafe-services
Project-URL: Documentation, https://github.com/geekcafe/geek-cafe-services/blob/main/README.md
Project-URL: Source Code, https://github.com/geekcafe/geek-cafe-services
Author-email: Eric Wilson <eric.wilson@geekcafe.com>
License: Geek Cafe Services Business Source License 1.0
License-File: LICENSE
Keywords: api gateway,aws,dynamodb,lambda,saas,serverless,services
Classifier: Development Status :: 4 - Beta
Classifier: Framework :: AWS CDK
Classifier: Intended Audience :: Developers
Classifier: License :: OSI Approved :: MIT License
Classifier: Programming Language :: Python :: 3
Classifier: Programming Language :: Python :: 3.8
Classifier: Programming Language :: Python :: 3.9
Classifier: Programming Language :: Python :: 3.10
Classifier: Programming Language :: Python :: 3.11
Classifier: Programming Language :: Python :: 3.12
Classifier: Topic :: Software Development :: Libraries :: Python Modules
Requires-Python: >=3.8
Requires-Dist: boto3-assist
Provides-Extra: dev
Requires-Dist: build; extra == 'dev'
Requires-Dist: twine; extra == 'dev'
